django_chain/__init__.py
django_chain/apps.py
django_chain/config.py
django_chain/exceptions.py
django_chain/mixins.py
django_chain/models.py
django_chain/urls.py
django_chain/validators.py
django_chain/views.py
django_chain/migrations/0001_initial.py
django_chain/migrations/0002_alter_chatsession_session_id.py
django_chain/migrations/__init__.py
django_chain/providers/__init__.py
django_chain/providers/fake.py
django_chain/providers/google.py
django_chain/providers/huggingface.py
django_chain/providers/openai.py
django_chain/providers/pgvector.py
django_chain/services/__init__.py
django_chain/services/vector_store_manager.py
django_chain/utils/__init__.py
django_chain/utils/langchain.py
django_chain/utils/llm_client.py
django_chain/utils/memory_manager.py
django_chain/utils/prompts.py
django_chain-0.2.0a4.dist-info/METADATA
django_chain-0.2.0a4.dist-info/WHEEL
django_chain-0.2.0a4.dist-info/licenses/LICENSE.txt
django_chain-0.2.0a4.dist-info/RECORD
