Metadata-Version: 2.4
Name: django-chain
Version: 0.2.0a4
Summary: A Django-based library for seamless LLM integration
Project-URL: homepage, https://github.com/Brian-Kariu/django-chain/
Project-URL: repository, https://github.com/Brian-Kariu/django-chain/
Project-URL: documentation, https://django-chain.onrender.com/introduction/design/
Project-URL: changelog, https://github.com/Brian-Kariu/django-chain/blob/main/CHANGELOG.md
Project-URL: Bug Tracker, https://github.com/Brian-Kariu/django-chain/issues
Author: Brian Kariu
License-Expression: MIT
License-File: LICENSE.txt
Keywords: django,langchain
Classifier: Development Status :: 3 - Alpha
Classifier: Framework :: Django
Classifier: Framework :: Django :: 4.2
Classifier: Framework :: Django :: 5.0
Classifier: Intended Audience :: Developers
Classifier: License :: OSI Approved :: MIT License
Classifier: Operating System :: OS Independent
Classifier: Programming Language :: Python :: 3
Classifier: Programming Language :: Python :: 3.9
Classifier: Programming Language :: Python :: 3.10
Classifier: Programming Language :: Python :: 3.11
Requires-Python: >=3.9
Requires-Dist: django>=4.0
Requires-Dist: langchain-community>=0.1.0
Requires-Dist: langchain-core>=0.1.0
Requires-Dist: langchain>=0.1.0
Requires-Dist: psycopg2-binary>=2.9.0
Provides-Extra: all
Requires-Dist: celery>=5.0; extra == 'all'
Requires-Dist: chromadb>=0.4.0; extra == 'all'
Requires-Dist: django-celery-beat>=2.0; extra == 'all'
Requires-Dist: django-celery-results>=2.0; extra == 'all'
Requires-Dist: langchain-community>=0.1.0; extra == 'all'
Requires-Dist: langchain-google-genai>=0.1.0; extra == 'all'
Requires-Dist: langchain-huggingface>=0.1.0; extra == 'all'
Requires-Dist: langchain-openai>=0.1.0; extra == 'all'
Requires-Dist: langchain-pinecone>=0.1.0; extra == 'all'
Requires-Dist: pgvector>=0.1.0; extra == 'all'
Requires-Dist: sentry-sdk>=1.0; extra == 'all'
Provides-Extra: celery
Requires-Dist: celery>=5.0; extra == 'celery'
Requires-Dist: django-celery-beat>=2.0; extra == 'celery'
Requires-Dist: django-celery-results>=2.0; extra == 'celery'
Provides-Extra: chroma
Requires-Dist: chromadb>=0.4.0; extra == 'chroma'
Requires-Dist: langchain-community>=0.1.0; extra == 'chroma'
Provides-Extra: dev
Requires-Dist: commitizen; extra == 'dev'
Requires-Dist: coverage>=7.0.0; extra == 'dev'
Requires-Dist: factory-boy>=3.3.0; extra == 'dev'
Requires-Dist: faker>=18.0.0; extra == 'dev'
Requires-Dist: model-bakery>=1.20.5; extra == 'dev'
Requires-Dist: mypy>=1.5.1; extra == 'dev'
Requires-Dist: pytest-asyncio>=0.21.0; extra == 'dev'
Requires-Dist: pytest-cov>=4.1.0; extra == 'dev'
Requires-Dist: pytest-django>=4.5.0; extra == 'dev'
Requires-Dist: pytest-html; extra == 'dev'
Requires-Dist: pytest>=7.0.0; extra == 'dev'
Requires-Dist: ruff>=0.1.0; extra == 'dev'
Provides-Extra: docs
Requires-Dist: mkdocs-gen-files; extra == 'docs'
Requires-Dist: mkdocs-literate-nav; extra == 'docs'
Requires-Dist: mkdocs-material; extra == 'docs'
Requires-Dist: mkdocs-section-index; extra == 'docs'
Requires-Dist: mkdocs==1.6.1; extra == 'docs'
Requires-Dist: mkdocstrings[python]; extra == 'docs'
Requires-Dist: pylinkvalidator; extra == 'docs'
Provides-Extra: google
Requires-Dist: langchain-google-genai>=0.1.0; extra == 'google'
Provides-Extra: huggingface
Requires-Dist: langchain-huggingface>=0.1.0; extra == 'huggingface'
Provides-Extra: openai
Requires-Dist: langchain-openai>=0.1.0; extra == 'openai'
Provides-Extra: pgvector
Requires-Dist: langchain-community>=0.1.0; extra == 'pgvector'
Requires-Dist: pgvector>=0.1.0; extra == 'pgvector'
Provides-Extra: pinecone
Requires-Dist: langchain-pinecone>=0.1.0; extra == 'pinecone'
Provides-Extra: sentry
Requires-Dist: sentry-sdk>=1.0; extra == 'sentry'
